akshateda/__init__.py
akshateda/eda.py
akshateda-0.1.0.dist-info/METADATA
akshateda-0.1.0.dist-info/WHEEL
akshateda-0.1.0.dist-info/top_level.txt
akshateda-0.1.0.dist-info/RECORD
