Metadata-Version: 2.4
Name: AKSHATEDA
Version: 0.1.0
Summary: An interactive Python package for automated Exploratory Data Analysis (EDA)
Home-page: https://github.com/yourusername/AKSHATEDA
Author: Your Name
Author-email: your@email.com
Classifier: Programming Language :: Python :: 3
Classifier: Operating System :: OS Independent
Requires-Python: >=3.6
Requires-Dist: pandas
Requires-Dist: numpy
Requires-Dist: matplotlib
Dynamic: author
Dynamic: author-email
Dynamic: classifier
Dynamic: description-content-type
Dynamic: home-page
Dynamic: requires-dist
Dynamic: requires-python
Dynamic: summary
